lsyflaskplugin_minio/__init__.py
lsyflaskplugin_minio/api.py
lsyflaskplugin_minio/error.py
lsyflaskplugin_minio-1.0.0.dist-info/METADATA
lsyflaskplugin_minio-1.0.0.dist-info/WHEEL
lsyflaskplugin_minio-1.0.0.dist-info/top_level.txt
lsyflaskplugin_minio-1.0.0.dist-info/RECORD
