Metadata-Version: 2.1
Name: lsyflaskplugin-minio
Version: 1.0.0
Summary: lsyflaskplugin_minio
Home-page: https://gitee.com/linkeddt/lsyflasksdkcore.git
Author: fhp
Author-email: chinafengheping@outlook.com
License: UNKNOWN
Platform: UNKNOWN
Requires-Dist: Flask (==1.1.2)
Requires-Dist: minio (==7.0.3)
